{
  "file-explorer": false,
  "global-search": true,
  "switcher": false,
  "graph": true,
  "backlink": true,
  "outgoing-link": false,
  "tag-pane": true,
  "page-preview": true,
  "daily-notes": false,
  "templates": true,
  "note-composer": false,
  "command-palette": true,
  "slash-command": false,
  "editor-status": false,
  "markdown-importer": false,
  "zk-prefixer": false,
  "random-note": false,
  "outline": true,
  "word-count": false,
  "slides": false,
  "audio-recorder": false,
  "workspaces": false,
  "file-recovery": true,
  "publish": false,
  "sync": false,
  "canvas": false,
  "bookmarks": false,
  "properties": false
}